MANIFEST.in
README-PYPI.md
README.md
setup.cfg
setup.py
capsule8/__init__.py
capsule8/exceptions.py
capsule8/sensor.py
capsule8/subscriptions.py
capsule8/utils.py
capsule8.egg-info/PKG-INFO
capsule8.egg-info/SOURCES.txt
capsule8.egg-info/dependency_links.txt
capsule8.egg-info/requires.txt
capsule8.egg-info/top_level.txt
capsule8/api/__init__.py
capsule8/api/v0/__init__.py
capsule8/api/v0/expression_pb2.py
capsule8/api/v0/expression_pb2_grpc.py
capsule8/api/v0/subscription_pb2.py
capsule8/api/v0/subscription_pb2_grpc.py
capsule8/api/v0/telemetry_event_pb2.py
capsule8/api/v0/telemetry_event_pb2_grpc.py
capsule8/api/v0/telemetry_service_pb2.py
capsule8/api/v0/telemetry_service_pb2_grpc.py
capsule8/api/v0/types_pb2.py
capsule8/api/v0/types_pb2_grpc.py