Metadata-Version: 2.1
Name: capsule8
Version: 1.13
Summary: capsule8 open source sensor python grpc bindings
Home-page: http://github.com/capsule8/api-python
Author: Alexander Comerford
Author-email: alex@capsule8.com
License: UNKNOWN
Platform: UNKNOWN
